azureml/__init__.py
azureml/automl/__init__.py
azureml/automl/dnn/__init__.py
azureml/automl/dnn/vision/__init__.py
azureml/automl/dnn/vision/classification/__init__.py
azureml/automl/dnn/vision/classification/runner.py
azureml/automl/dnn/vision/classification/common/__init__.py
azureml/automl/dnn/vision/classification/common/classification_utils.py
azureml/automl/dnn/vision/classification/common/constants.py
azureml/automl/dnn/vision/classification/common/transforms.py
azureml/automl/dnn/vision/classification/inference/__init__.py
azureml/automl/dnn/vision/classification/inference/score.py
azureml/automl/dnn/vision/classification/io/__init__.py
azureml/automl/dnn/vision/classification/io/read/__init__.py
azureml/automl/dnn/vision/classification/io/read/dataloader.py
azureml/automl/dnn/vision/classification/io/read/dataset_wrappers.py
azureml/automl/dnn/vision/classification/io/read/utils.py
azureml/automl/dnn/vision/classification/io/write/__init__.py
azureml/automl/dnn/vision/classification/io/write/featurize_script.py
azureml/automl/dnn/vision/classification/io/write/score_script.py
azureml/automl/dnn/vision/classification/io/write/score_script_utils.py
azureml/automl/dnn/vision/classification/models/__init__.py
azureml/automl/dnn/vision/classification/models/base_model_wrapper.py
azureml/automl/dnn/vision/classification/models/classification_model_wrappers.py
azureml/automl/dnn/vision/classification/trainer/__init__.py
azureml/automl/dnn/vision/classification/trainer/criterion.py
azureml/automl/dnn/vision/classification/trainer/train.py
azureml/automl/dnn/vision/common/NOTICE
azureml/automl/dnn/vision/common/__init__.py
azureml/automl/dnn/vision/common/aml_dataset_base_wrapper.py
azureml/automl/dnn/vision/common/artifacts_utils.py
azureml/automl/dnn/vision/common/average_meter.py
azureml/automl/dnn/vision/common/base_model_factory.py
azureml/automl/dnn/vision/common/base_model_settings.py
azureml/automl/dnn/vision/common/constants.py
azureml_automl_dnn_vision-1.61.0.post1.dist-info/licenses/LICENSE.txt
azureml_automl_dnn_vision-1.61.0.post1.dist-info/METADATA
azureml_automl_dnn_vision-1.61.0.post1.dist-info/WHEEL
azureml_automl_dnn_vision-1.61.0.post1.dist-info/namespace_packages.txt
azureml_automl_dnn_vision-1.61.0.post1.dist-info/top_level.txt
azureml_automl_dnn_vision-1.61.0.post1.dist-info/RECORD
